moveread/pipelines/tatr/__init__.py
moveread/pipelines/tatr/__init__.pyi
moveread/pipelines/tatr/cli.py
moveread/pipelines/tatr/pipeline.py
moveread_pipelines_tatr-0.1.0.dist-info/METADATA
moveread_pipelines_tatr-0.1.0.dist-info/WHEEL
moveread_pipelines_tatr-0.1.0.dist-info/entry_points.txt
moveread_pipelines_tatr-0.1.0.dist-info/top_level.txt
moveread_pipelines_tatr-0.1.0.dist-info/RECORD
