Metadata-Version: 2.1
Name: moveread-pipelines-tatr
Version: 0.1.0
Summary: Moveread Table Transformer pipeline
Author-email: Marcel Claramunt <marcel@moveread.com>
Project-URL: repo, https://github.com/moveread/pipelines.git
Requires-Python: >=3.10
Requires-Dist: pipeteer
Requires-Dist: fastapi
Requires-Dist: uvicorn
Requires-Dist: pure-cv
Requires-Dist: scoresheet-models
Provides-Extra: run
Requires-Dist: torch; extra == "run"
Requires-Dist: torchvision; extra == "run"
Requires-Dist: torchaudio; extra == "run"
Requires-Dist: moveread-tatr; extra == "run"
Requires-Dist: python-kv; extra == "run"
